{
  "name": {
    "en": "Water heater"
  },
  "class": "heater",
  "capabilities": [
    "measure_power",
    "alarm_generic",
    "measure_power_produced",
    "target_temperature",
    "measure_temperature",
    "measure_temperature.bottom",
    "measure_efficiency"
  ],
  "capabilitiesOptions": {
    "alarm_generic": { "title": { "en": "Heating" } },
    "measure_temperature": { 
      "title": { "en": "Temperature Top" },
      "min": 10,
      "max": 80,
      "step": 1,
      "decimals": 0
    },
    "measure_temperature.bottom": { 
      "title": { "en": "Temperature Bottom" },
      "decimals": 0
    },
    "target_temperature": { 
      "min": 30,
      "max": 50,
      "step": 1,
      "decimals": 0
    }
  },
  "platforms": [
    "local"
  ],
  "connectivity": [
    "lan" 
  ],
  "images": {
    "small": "/drivers/water/assets/images/small.png",
    "large": "/drivers/water/assets/images/large.png",
    "xlarge": "/drivers/water/assets/images/xlarge.png"
  },
  "pair": [
    {
      "id": "list_devices",
      "template": "list_devices",
      "navigation": { "next": "add_devices" },
      "options": { "singular": true }
    },
    {
      "id": "add_devices",
      "template": "add_devices"
    }
  ]
}